Workbook

Sheet INÍCIO
B2: ORGANIZADOR DE IMPOSTO DE RENDA
B3: Reúna e confira seus dados antes de abrir o programa da Receita Federal
B5: ANO-CALENDÁRIO | C5: 2026 | E5: TITULAR | F5: =IF(TITULAR!C8="","(preencha a aba TITULAR)",TITULAR!C8) -> Ana Beatriz Exemplo Souza
B6: Amarelo com texto azul = preencher · Células brancas e cinza = fórmulas (protegidas, sem senha) · As linhas de exemplo (fictícias) podem ser apagadas.
B7: MENU
B8: 1 · TITULAR | D8: 2 · RENDIMENTOS | F8: 3 · ENTRADAS | H8: 4 · DEDUÇÕES
B9: Dados pessoais | D9: Saldos e informes dos bancos | F9: Holerites, PJ e outras receitas | H9: Saúde, educação e outras
B10: =IF(SUMPRODUCT(--(LEFT(TITULAR!$D$8:$D$31,1)="✔"))=(SUMPRODUCT(--(LEFT(TITULAR!$D$8:$D$31,1)="✔"))+SUMPRODUCT(--(LEFT(TITULAR!$D$8:$D$31,1)="⚠"))+SUMPRODUCT(--(LEFT(TITULAR!$D$8:$D$31,1)="✖"))),"✔ Completo",SUMPRODUCT(--(LEFT(TITULAR!$D$8:$D$31,1)="✔"))&" de "&(SUMPRODUCT(--(LEFT(TITULAR!$D$8:$D$31,1)="✔"))+SUMPRODUCT(--(LEFT(TITULAR!$D$8:$D$31,1)="⚠"))+SUMPRODUCT(--(LEFT(TITULAR!$D$8:$D$31,1)="✖")))&" campos ok") -> ✔ Completo | D10: =IF(SUMPRODUCT(--(LEN(RENDIMENTOS!$J$11:$J$25)>0))=0,"⚠ Nenhum banco lançado",IF(RENDIMENTOS!$E$8=0,"✔ "&SUMPRODUCT(--(LEN(RENDIMENTOS!$J$11:$J$25)>0))&" lançamento(s) ok",RENDIMENTOS!$E$8&" informe(s) pendente(s)")) -> ✔ 1 lançamento(s) ok | F10: =IF(ENTRADAS!$K$16=0,"⚠ Nenhuma entrada",ENTRADAS!$K$16&" lançamento(s)") -> 1 lançamento(s) | H10: =IF(DEDUÇÕES!$K$16=0,"Opcional · nada lançado",DEDUÇÕES!$K$16&" lançamento(s)") -> 1 lançamento(s)
B12: RESUMO DO ANO
B13: ENTRADAS (BRUTO) | D13: IR RETIDO NA FONTE | F13: SALDO BANCÁRIO 31/12 | H13: DEDUÇÕES LANÇADAS
B14: =ENTRADAS!$K$14 -> 5200 | D14: =ENTRADAS!$L$14 -> 410.35 | F14: =RENDIMENTOS!$E$26 -> 8450.75 | H14: =DEDUÇÕES!$K$14 -> 480
B16: ENTRADAS MÊS A MÊS
B17: Mês | C17: Bruto (R$) | D17: % do ano
B18: Janeiro | C18: =SUMIFS(ENTRADAS!$E$8:$E$207,ENTRADAS!$B$8:$B$207,">="&DATE(ANO_BASE,1,1),ENTRADAS!$B$8:$B$207,"<"&DATE(ANO_BASE,2,1)) -> 5200 | D18: =IF($C$30=0,0,C18/$C$30) -> 1
B19: Fevereiro | C19: =SUMIFS(ENTRADAS!$E$8:$E$207,ENTRADAS!$B$8:$B$207,">="&DATE(ANO_BASE,2,1),ENTRADAS!$B$8:$B$207,"<"&DATE(ANO_BASE,3,1)) -> 0 | D19: =IF($C$30=0,0,C19/$C$30) -> 0
B20: Março | C20: =SUMIFS(ENTRADAS!$E$8:$E$207,ENTRADAS!$B$8:$B$207,">="&DATE(ANO_BASE,3,1),ENTRADAS!$B$8:$B$207,"<"&DATE(ANO_BASE,4,1)) -> 0 | D20: =IF($C$30=0,0,C20/$C$30) -> 0
B21: Abril | C21: =SUMIFS(ENTRADAS!$E$8:$E$207,ENTRADAS!$B$8:$B$207,">="&DATE(ANO_BASE,4,1),ENTRADAS!$B$8:$B$207,"<"&DATE(ANO_BASE,5,1)) -> 0 | D21: =IF($C$30=0,0,C21/$C$30) -> 0
B22: Maio | C22: =SUMIFS(ENTRADAS!$E$8:$E$207,ENTRADAS!$B$8:$B$207,">="&DATE(ANO_BASE,5,1),ENTRADAS!$B$8:$B$207,"<"&DATE(ANO_BASE,6,1)) -> 0 | D22: =IF($C$30=0,0,C22/$C$30) -> 0
B23: Junho | C23: =SUMIFS(ENTRADAS!$E$8:$E$207,ENTRADAS!$B$8:$B$207,">="&DATE(ANO_BASE,6,1),ENTRADAS!$B$8:$B$207,"<"&DATE(ANO_BASE,7,1)) -> 0 | D23: =IF($C$30=0,0,C23/$C$30) -> 0
B24: Julho | C24: =SUMIFS(ENTRADAS!$E$8:$E$207,ENTRADAS!$B$8:$B$207,">="&DATE(ANO_BASE,7,1),ENTRADAS!$B$8:$B$207,"<"&DATE(ANO_BASE,8,1)) -> 0 | D24: =IF($C$30=0,0,C24/$C$30) -> 0
B25: Agosto | C25: =SUMIFS(ENTRADAS!$E$8:$E$207,ENTRADAS!$B$8:$B$207,">="&DATE(ANO_BASE,8,1),ENTRADAS!$B$8:$B$207,"<"&DATE(ANO_BASE,9,1)) -> 0 | D25: =IF($C$30=0,0,C25/$C$30) -> 0
B26: Setembro | C26: =SUMIFS(ENTRADAS!$E$8:$E$207,ENTRADAS!$B$8:$B$207,">="&DATE(ANO_BASE,9,1),ENTRADAS!$B$8:$B$207,"<"&DATE(ANO_BASE,10,1)) -> 0 | D26: =IF($C$30=0,0,C26/$C$30) -> 0
B27: Outubro | C27: =SUMIFS(ENTRADAS!$E$8:$E$207,ENTRADAS!$B$8:$B$207,">="&DATE(ANO_BASE,10,1),ENTRADAS!$B$8:$B$207,"<"&DATE(ANO_BASE,11,1)) -> 0 | D27: =IF($C$30=0,0,C27/$C$30) -> 0
B28: Novembro | C28: =SUMIFS(ENTRADAS!$E$8:$E$207,ENTRADAS!$B$8:$B$207,">="&DATE(ANO_BASE,11,1),ENTRADAS!$B$8:$B$207,"<"&DATE(ANO_BASE,12,1)) -> 0 | D28: =IF($C$30=0,0,C28/$C$30) -> 0
B29: Dezembro | C29: =SUMIFS(ENTRADAS!$E$8:$E$207,ENTRADAS!$B$8:$B$207,">="&DATE(ANO_BASE,12,1),ENTRADAS!$B$8:$B$207,"<"&DATE(ANO_BASE,13,1)) -> 0 | D29: =IF($C$30=0,0,C29/$C$30) -> 0
B30: TOTAL | C30: =SUM(C18:C29) -> 5200 | D30: =SUM(D18:D29) -> 1
B31: =IF(ROUND(C30-ENTRADAS!$K$14,2)=0,"✔ Soma confere com a aba ENTRADAS","⚠ Há entradas fora do ano-calendário") -> ✔ Soma confere com a aba ENTRADAS
B33: LINKS RÁPIDOS (OFICIAIS)
B34: Receita Federal ↗ | D34: Portal oficial: download do programa do IRPF, prazos e regras.
B35: Meu Imposto de Renda ↗ | D35: Declaração pelo navegador ou app (conta gov.br prata ou ouro).
B36: Portal e-CAC ↗ | D36: Atendimento virtual: pendências, extratos e declaração pré-preenchida.
B37: Conta gov.br ↗ | D37: Crie ou aumente o nível da sua conta antes de declarar.
B39: Planilha de apoio à organização dos documentos; não substitui o programa oficial nem orientação contábil. Confira sempre as regras do ano na Receita Federal.

Sheet TITULAR
B2: 1 · DADOS DO TITULAR
B3: Informações pessoais usadas para abrir a declaração
B4: ◀ Menu principal | D4: Próxima etapa: Rendimentos ▶
B5: Preencha as células amarelas (texto azul). A coluna de status confere cada campo. Os dados atuais são um EXEMPLO fictício — sobrescreva com os seus.
B7: IDENTIFICAÇÃO
B8: Nome completo | C8: Ana Beatriz Exemplo Souza | D8: =IF(C8="","⚠ Obrigatório","✔") -> ✔
B9: CPF (somente números) | C9: 52998224725 | D9: =IF(C9="","⚠ Obrigatório",IF(AND(MOD(C9,11111111111)<>0,MOD(MOD(SUMPRODUCT(--MID(TEXT(C9,"00000000000"),{1,2,3,4,5,6,7,8,9},1),{10,9,8,7,6,5,4,3,2})*10,11),10)=--MID(TEXT(C9,"00000000000"),10,1),MOD(MOD(SUMPRODUCT(--MID(TEXT(C9,"00000000000"),{1,2,3,4,5,6,7,8,9,10},1),{11,10,9,8,7,6,5,4,3,2})*10,11),10)=--MID(TEXT(C9,"00000000000"),11,1)),"✔ CPF válido","✖ CPF inválido")) -> ✔ CPF válido
B10: Data de nascimento | C10: 33007 | D10: =IF(C10="","⚠ Obrigatório","✔ "&DATEDIF(C10,TODAY(),"Y")&" anos") -> ✔ 36 anos
B11: Título de eleitor (12 dígitos) | C11: 123456789012 | D11: =IF(C11="","⚠ Obrigatório","✔") -> ✔
B12: Estado civil | C12: Casado(a) | D12: =IF(C12="","⚠ Obrigatório","✔") -> ✔
B13: Nome do cônjuge | C13: Carlos Exemplo Souza | D13: =IF(OR(C12="Casado(a)",C12="União estável"),IF(C13="","⚠ Informe o cônjuge","✔"),"Opcional") -> ✔
B14: ENDEREÇO
B15: Logradouro | C15: Rua das Acácias | D15: =IF(C15="","⚠ Obrigatório","✔") -> ✔
B16: Número | C16: 250 | D16: =IF(C16="","⚠ Obrigatório","✔") -> ✔
B17: Complemento (opcional) | C17: Apto 41 | D17: Opcional
B18: Bairro | C18: Centro | D18: =IF(C18="","⚠ Obrigatório","✔") -> ✔
B19: Cidade | C19: Curitiba | D19: =IF(C19="","⚠ Obrigatório","✔") -> ✔
B20: UF | C20: PR | D20: =IF(C20="","⚠ Obrigatório","✔") -> ✔
B21: CEP (somente números) | C21: 80010000 | D21: =IF(C21="","⚠ Obrigatório","✔") -> ✔
B22: Endereço completo (gerado) | C22: =IF(C15="","",C15&", "&C16&IF(C17="",""," - "&C17)&" · "&C18&" · "&C19&"/"&C20&" · CEP "&TEXT(C21,"00000-000")) -> Rua das Acácias, 250 - Apto 41 · Centro · Curitiba/PR · CEP 80010-000 | D22: Gerado automaticamente
B23: CONTATO
B24: Telefone fixo (opcional) | C24: 4133334444 | D24: Opcional
B25: Celular | C25: 41999998888 | D25: =IF(C25="","⚠ Obrigatório","✔") -> ✔
B26: E-mail | C26: ana.exemplo@email.com | D26: =IF(C26="","⚠ Obrigatório",IF(ISNUMBER(FIND("@",C26)),IF(ISNUMBER(FIND(".",C26,FIND("@",C26))),"✔","✖ E-mail inválido"),"✖ E-mail inválido")) -> ✔
B27: SITUAÇÃO DA DECLARAÇÃO
B28: Houve alterações desde a entrega anterior? | C28: NÃO | D28: =IF(C28="","⚠ Obrigatório","✔") -> ✔
B29: Cônjuge entra como dependente? | C29: NÃO | D29: =IF(C29="","⚠ Obrigatório","✔") -> ✔
B30: Residente no exterior? | C30: NÃO | D30: =IF(C30="","⚠ Obrigatório","✔") -> ✔
B31: Possui outros dependentes? | C31: NÃO | D31: =IF(C31="","⚠ Obrigatório","✔") -> ✔

Sheet RENDIMENTOS
B2: 2 · RENDIMENTOS BANCÁRIOS
B3: Saldos em 31/12 e rendimentos do ano, por instituição (o que consta nos informes dos bancos)
B4: ◀ Menu principal | J4: Próxima etapa: Entradas ▶
B5: Um banco por linha (repita o banco se tiver mais de um produto). Marque se já recebeu o informe e cole o nome do arquivo ou o link do PDF — a coluna ‘Abrir’ cria o atalho. Linha 1 = EXEMPLO fictício.
C7: SALDO TOTAL EM 31/12 | D7: RENDIMENTOS NO ANO | E7: INFORMES PENDENTES
C8: =SUM(E11:E25) -> 8450.75 | D8: =SUM(F11:F25) -> 312.4 | E8: =SUMPRODUCT(--(LEFT(J11:J25,1)="⚠")) -> 0
B10: Nº | C10: Banco / instituição | D10: Tipo de produto | E10: Saldo em 31/12 (R$) | F10: Rendimentos no ano (R$) | G10: Informe recebido? | H10: Arquivo ou link do informe | I10: Abrir | J10: Status
B11: 1 | C11: 260 - Nubank | D11: Conta corrente | E11: 8450.75 | F11: 312.4 | G11: SIM | H11: informe_nubank_2026.pdf | I11: =IF(H11="","",HYPERLINK(H11,"Abrir ↗")) -> Abrir ↗ | J11: =IF(AND(C11="",E11="",F11=""),"",IF(OR(C11="",AND(E11="",F11="")),"⚠ Incompleto",IF(G11="SIM","✔ Ok","⚠ Falta informe"))) -> ✔ Ok
B12: 2 | I12: =IF(H12="","",HYPERLINK(H12,"Abrir ↗")) | J12: =IF(AND(C12="",E12="",F12=""),"",IF(OR(C12="",AND(E12="",F12="")),"⚠ Incompleto",IF(G12="SIM","✔ Ok","⚠ Falta informe")))
B13: 3 | I13: =IF(H13="","",HYPERLINK(H13,"Abrir ↗")) | J13: =IF(AND(C13="",E13="",F13=""),"",IF(OR(C13="",AND(E13="",F13="")),"⚠ Incompleto",IF(G13="SIM","✔ Ok","⚠ Falta informe")))
B14: 4 | I14: =IF(H14="","",HYPERLINK(H14,"Abrir ↗")) | J14: =IF(AND(C14="",E14="",F14=""),"",IF(OR(C14="",AND(E14="",F14="")),"⚠ Incompleto",IF(G14="SIM","✔ Ok","⚠ Falta informe")))
B15: 5 | I15: =IF(H15="","",HYPERLINK(H15,"Abrir ↗")) | J15: =IF(AND(C15="",E15="",F15=""),"",IF(OR(C15="",AND(E15="",F15="")),"⚠ Incompleto",IF(G15="SIM","✔ Ok","⚠ Falta informe")))
B16: 6 | I16: =IF(H16="","",HYPERLINK(H16,"Abrir ↗")) | J16: =IF(AND(C16="",E16="",F16=""),"",IF(OR(C16="",AND(E16="",F16="")),"⚠ Incompleto",IF(G16="SIM","✔ Ok","⚠ Falta informe")))
B17: 7 | I17: =IF(H17="","",HYPERLINK(H17,"Abrir ↗")) | J17: =IF(AND(C17="",E17="",F17=""),"",IF(OR(C17="",AND(E17="",F17="")),"⚠ Incompleto",IF(G17="SIM","✔ Ok","⚠ Falta informe")))
B18: 8 | I18: =IF(H18="","",HYPERLINK(H18,"Abrir ↗")) | J18: =IF(AND(C18="",E18="",F18=""),"",IF(OR(C18="",AND(E18="",F18="")),"⚠ Incompleto",IF(G18="SIM","✔ Ok","⚠ Falta informe")))
B19: 9 | I19: =IF(H19="","",HYPERLINK(H19,"Abrir ↗")) | J19: =IF(AND(C19="",E19="",F19=""),"",IF(OR(C19="",AND(E19="",F19="")),"⚠ Incompleto",IF(G19="SIM","✔ Ok","⚠ Falta informe")))
B20: 10 | I20: =IF(H20="","",HYPERLINK(H20,"Abrir ↗")) | J20: =IF(AND(C20="",E20="",F20=""),"",IF(OR(C20="",AND(E20="",F20="")),"⚠ Incompleto",IF(G20="SIM","✔ Ok","⚠ Falta informe")))
B21: 11 | I21: =IF(H21="","",HYPERLINK(H21,"Abrir ↗")) | J21: =IF(AND(C21="",E21="",F21=""),"",IF(OR(C21="",AND(E21="",F21="")),"⚠ Incompleto",IF(G21="SIM","✔ Ok","⚠ Falta informe")))
B22: 12 | I22: =IF(H22="","",HYPERLINK(H22,"Abrir ↗")) | J22: =IF(AND(C22="",E22="",F22=""),"",IF(OR(C22="",AND(E22="",F22="")),"⚠ Incompleto",IF(G22="SIM","✔ Ok","⚠ Falta informe")))
B23: 13 | I23: =IF(H23="","",HYPERLINK(H23,"Abrir ↗")) | J23: =IF(AND(C23="",E23="",F23=""),"",IF(OR(C23="",AND(E23="",F23="")),"⚠ Incompleto",IF(G23="SIM","✔ Ok","⚠ Falta informe")))
... B25: 15 | I25: =IF(H25="","",HYPERLINK(H25,"Abrir ↗")) | J25: =IF(AND(C25="",E25="",F25=""),"",IF(OR(C25="",AND(E25="",F25="")),"⚠ Incompleto",IF(G25="SIM","✔ Ok","⚠ Falta informe")))
B26: TOTAL | E26: =SUM(E11:E25) -> 8450.75 | F26: =SUM(F11:F25) -> 312.4

Sheet ENTRADAS
B2: 3 · ENTRADAS DO ANO
B3: Holerites, notas de PJ e demais receitas, lançamento por lançamento
B4: ◀ Menu principal | H4: Próxima etapa: Deduções ▶
B5: Lance cada recebimento em uma linha. A data precisa estar dentro do ano-calendário definido no menu e o IR retido não pode passar do valor bruto. Linha 1 = EXEMPLO fictício.
B7: Data | C7: Categoria | D7: Fonte pagadora | E7: Valor bruto (R$) | F7: IR retido (R$) | G7: Valor líquido (R$) | H7: Observações | J7: CATEGORIA | K7: TOTAL BRUTO | L7: IR RETIDO
B8: 46052 | C8: Holerite (CLT) | D8: Empresa Exemplo Ltda | E8: 5200 | F8: 410.35 | G8: =IF(E8="","",E8-F8) -> 4789.65 | H8: Salário de janeiro | J8: =LISTAS!$B$2 -> Holerite (CLT) | K8: =SUMIF($C$8:$C$207,J8,$E$8:$E$207) -> 5200 | L8: =SUMIF($C$8:$C$207,J8,$F$8:$F$207) -> 410.35
G9: =IF(E9="","",E9-F9) | J9: =LISTAS!$B$3 -> Pró-labore | K9: =SUMIF($C$8:$C$207,J9,$E$8:$E$207) -> 0 | L9: =SUMIF($C$8:$C$207,J9,$F$8:$F$207) -> 0
G10: =IF(E10="","",E10-F10) | J10: =LISTAS!$B$4 -> CNPJ / PJ | K10: =SUMIF($C$8:$C$207,J10,$E$8:$E$207) -> 0 | L10: =SUMIF($C$8:$C$207,J10,$F$8:$F$207) -> 0
G11: =IF(E11="","",E11-F11) | J11: =LISTAS!$B$5 -> Freelance / Autônomo | K11: =SUMIF($C$8:$C$207,J11,$E$8:$E$207) -> 0 | L11: =SUMIF($C$8:$C$207,J11,$F$8:$F$207) -> 0
G12: =IF(E12="","",E12-F12) | J12: =LISTAS!$B$6 -> Aluguel recebido | K12: =SUMIF($C$8:$C$207,J12,$E$8:$E$207) -> 0 | L12: =SUMIF($C$8:$C$207,J12,$F$8:$F$207) -> 0
G13: =IF(E13="","",E13-F13) | J13: =LISTAS!$B$7 -> Outros | K13: =SUMIF($C$8:$C$207,J13,$E$8:$E$207) -> 0 | L13: =SUMIF($C$8:$C$207,J13,$F$8:$F$207) -> 0
G14: =IF(E14="","",E14-F14) | J14: TOTAL | K14: =SUM(E8:E207) -> 5200 | L14: =SUM(F8:F207) -> 410.35
G15: =IF(E15="","",E15-F15)
G16: =IF(E16="","",E16-F16) | J16: Lançamentos | K16: =COUNT(B8:B207) -> 1
G17: =IF(E17="","",E17-F17) | J17: Total líquido | K17: =SUM(G8:G207) -> 4789.65
G18: =IF(E18="","",E18-F18) | J18: Conferência (categorias × total) | K18: =IF(ROUND(SUM(K8:K13)-K14,2)=0,"✔ Confere","⚠ Há valores sem categoria") -> ✔ Confere
G19: =IF(E19="","",E19-F19)
G20: =IF(E20="","",E20-F20)
G21: =IF(E21="","",E21-F21)
G22: =IF(E22="","",E22-F22)
G23: =IF(E23="","",E23-F23)
G24: =IF(E24="","",E24-F24)
G25: =IF(E25="","",E25-F25)
G26: =IF(E26="","",E26-F26)
G27: =IF(E27="","",E27-F27)
G28: =IF(E28="","",E28-F28)
G29: =IF(E29="","",E29-F29)
G30: =IF(E30="","",E30-F30)
... G207: =IF(E207="","",E207-F207)

Sheet DEDUÇÕES
B2: 4 · DEDUÇÕES E DESPESAS
B3: Saúde, educação, previdência privada e outras despesas que podem abater do imposto
B4: ◀ Menu principal | G4: Voltar ao menu ▶
B5: Guarde o comprovante de cada despesa e registre o nome do arquivo ou o link. Esta aba só soma os valores — confira os limites e regras de dedução vigentes no site da Receita. Linha 1 = EXEMPLO fictício.
B7: Data | C7: Tipo | D7: Prestador / beneficiário | E7: CPF ou CNPJ do prestador | F7: Valor (R$) | G7: Comprovante (arquivo ou link) | H7: Abrir | J7: TIPO | K7: TOTAL (R$)
B8: 46093 | C8: Saúde | D8: Clínica Exemplo | E8: 12.345.678/0001-90 | F8: 480 | G8: recibo_clinica_0312.pdf | H8: =IF(G8="","",HYPERLINK(G8,"Abrir ↗")) -> Abrir ↗ | J8: =LISTAS!$D$2 -> Saúde | K8: =SUMIF($C$8:$C$107,J8,$F$8:$F$107) -> 480
H9: =IF(G9="","",HYPERLINK(G9,"Abrir ↗")) | J9: =LISTAS!$D$3 -> Educação | K9: =SUMIF($C$8:$C$107,J9,$F$8:$F$107) -> 0
H10: =IF(G10="","",HYPERLINK(G10,"Abrir ↗")) | J10: =LISTAS!$D$4 -> Previdência privada (PGBL) | K10: =SUMIF($C$8:$C$107,J10,$F$8:$F$107) -> 0
H11: =IF(G11="","",HYPERLINK(G11,"Abrir ↗")) | J11: =LISTAS!$D$5 -> Pensão alimentícia | K11: =SUMIF($C$8:$C$107,J11,$F$8:$F$107) -> 0
H12: =IF(G12="","",HYPERLINK(G12,"Abrir ↗")) | J12: =LISTAS!$D$6 -> Doações incentivadas | K12: =SUMIF($C$8:$C$107,J12,$F$8:$F$107) -> 0
H13: =IF(G13="","",HYPERLINK(G13,"Abrir ↗")) | J13: =LISTAS!$D$7 -> Outras | K13: =SUMIF($C$8:$C$107,J13,$F$8:$F$107) -> 0
H14: =IF(G14="","",HYPERLINK(G14,"Abrir ↗")) | J14: TOTAL | K14: =SUM(F8:F107) -> 480
H15: =IF(G15="","",HYPERLINK(G15,"Abrir ↗"))
H16: =IF(G16="","",HYPERLINK(G16,"Abrir ↗")) | J16: Lançamentos | K16: =COUNT(B8:B107) -> 1
H17: =IF(G17="","",HYPERLINK(G17,"Abrir ↗"))
H18: =IF(G18="","",HYPERLINK(G18,"Abrir ↗"))
H19: =IF(G19="","",HYPERLINK(G19,"Abrir ↗"))
H20: =IF(G20="","",HYPERLINK(G20,"Abrir ↗"))
H21: =IF(G21="","",HYPERLINK(G21,"Abrir ↗"))
H22: =IF(G22="","",HYPERLINK(G22,"Abrir ↗"))
H23: =IF(G23="","",HYPERLINK(G23,"Abrir ↗"))
H24: =IF(G24="","",HYPERLINK(G24,"Abrir ↗"))
H25: =IF(G25="","",HYPERLINK(G25,"Abrir ↗"))
H26: =IF(G26="","",HYPERLINK(G26,"Abrir ↗"))
H27: =IF(G27="","",HYPERLINK(G27,"Abrir ↗"))
H28: =IF(G28="","",HYPERLINK(G28,"Abrir ↗"))
... H107: =IF(G107="","",HYPERLINK(G107,"Abrir ↗"))

Sheet LISTAS
A1: Bancos | B1: Categorias de entrada | C1: Tipos de produto | D1: Tipos de dedução | E1: Sim/Não | F1: UF | G1: Estado civil | I1: Aba de apoio das listas suspensas. Para incluir um item, escreva-o no fim da coluna e ajuste o nome definido (Fórmulas > Gerenciador de Nomes).
A2: 1 - Banco do Brasil | B2: Holerite (CLT) | C2: Conta corrente | D2: Saúde | E2: SIM | F2: AC | G2: Solteiro(a)
A3: 102 - XP Investimentos CCTVM S.A. | B3: Pró-labore | C3: Poupança | D3: Educação | E3: NÃO | F3: AL | G3: Casado(a)
A4: 104 - Caixa Econômica Federal | B4: CNPJ / PJ | C4: Renda fixa (CDB/LCI/LCA) | D4: Previdência privada (PGBL) | F4: AP | G4: União estável
A5: 119 - Banco Western Union do Brasil | B5: Freelance / Autônomo | C5: Fundos de investimento | D5: Pensão alimentícia | F5: AM | G5: Divorciado(a)
A6: 184 - Banco Itaú BBA S.A. | B6: Aluguel recebido | C6: Ações / FIIs / ETFs | D6: Doações incentivadas | F6: BA | G6: Separado(a)
A7: 197 - Stone Pagamentos | B7: Outros | C7: Outros | D7: Outras | F7: CE | G7: Viúvo(a)
A8: 208 - Banco BTG Pactual | F8: DF
A9: 212 - Banco Original | F9: ES
A10: 218 - Banco Bonsucesso | F10: GO
A11: 229 - Banco Cruzeiro do Sul | F11: MA
A12: 237 - Banco Bradesco | F12: MT
A13: 24 - Banco de Pernambuco | F13: MS
A14: 241 - Banco Clássico | F14: MG
A15: 250 - Banco de Crédito e Varejo (BCV) | F15: PA
A16: 260 - Nubank | F16: PB
A17: 29 - Banco do Estado do Rio de Janeiro | F17: PR
A18: 290 - PagBank | F18: PE
A19: 3 - Banco da Amazônia | F19: PI
... A28: 422 - Banco Safra | F28: TO
A29: 44 - Banco BVA
A30: 464 - Banco Sumitomo Mitsui Brasileiro
A31: 477 - Citibank
A32: 600 - Banco Luso Brasileiro
A33: 604 - Banco Industrial do Brasil
A34: 610 - Banco VR
A35: 62 - Hipercard Banco Múltiplo
A36: 634 - Banco Triângulo
A37: 65 - Banco Lemon
A38: 654 - Banco AJ Renner
A39: 655 - Banco Votorantim
A40: 66 - Banco Morgan Stanley
... A51: 82 - Banco Topázio
